lazyEEG/.gitignore
lazyEEG/LICENSE
lazyEEG/README.md
lazyEEG/__init__.py
lazyEEG/changelog.md
lazyEEG/default.py
lazyEEG/doc.md
lazyEEG/group.py
lazyEEG/structure.py
lazyEEG/__pycache__/__init__.cpython-35.pyc
lazyEEG/__pycache__/__init__.cpython-36.pyc
lazyEEG/__pycache__/default.cpython-35.pyc
lazyEEG/__pycache__/default.cpython-36.pyc
lazyEEG/__pycache__/group.cpython-35.pyc
lazyEEG/__pycache__/group.cpython-36.pyc
lazyEEG/__pycache__/parameter.cpython-35.pyc
lazyEEG/__pycache__/parameter.cpython-36.pyc
lazyEEG/__pycache__/structure.cpython-36.pyc
lazyEEG/algorithms/__init__.py
lazyEEG/algorithms/basic.py
lazyEEG/algorithms/classifier.py
lazyEEG/algorithms/cluster_models.py
lazyEEG/algorithms/erp.py
lazyEEG/algorithms/other.py
lazyEEG/algorithms/similiarity.py
lazyEEG/algorithms/spectrum.py
lazyEEG/algorithms/topo.py
lazyEEG/algorithms/__pycache__/__init__.cpython-36.pyc
lazyEEG/algorithms/__pycache__/basic.cpython-36.pyc
lazyEEG/algorithms/__pycache__/classifier.cpython-36.pyc
lazyEEG/algorithms/__pycache__/cluster_models.cpython-36.pyc
lazyEEG/algorithms/__pycache__/clustering.cpython-36.pyc
lazyEEG/algorithms/__pycache__/erp.cpython-36.pyc
lazyEEG/algorithms/__pycache__/general.cpython-36.pyc
lazyEEG/algorithms/__pycache__/gfp.cpython-36.pyc
lazyEEG/algorithms/__pycache__/other.cpython-36.pyc
lazyEEG/algorithms/__pycache__/similiarity.cpython-36.pyc
lazyEEG/algorithms/__pycache__/spectrum.cpython-36.pyc
lazyEEG/algorithms/__pycache__/tanova.cpython-36.pyc
lazyEEG/algorithms/__pycache__/topo.cpython-36.pyc
lazyEEG/data/montages/standard-10-5-cap385.elp
lazyEEG/graph/__init__.py
lazyEEG/graph/figure_group - 副本.py
lazyEEG/graph/figure_group.py
lazyEEG/graph/figure_unit - 副本.py
lazyEEG/graph/figure_unit.py
lazyEEG/graph/__pycache__/__init__.cpython-36.pyc
lazyEEG/graph/__pycache__/draw.cpython-36.pyc
lazyEEG/graph/__pycache__/figure_group.cpython-36.pyc
lazyEEG/graph/__pycache__/figure_unit.cpython-36.pyc
lazyEEG-0.8.0.1.dist-info/DESCRIPTION.rst
lazyEEG-0.8.0.1.dist-info/METADATA
lazyEEG-0.8.0.1.dist-info/RECORD
lazyEEG-0.8.0.1.dist-info/WHEEL
lazyEEG-0.8.0.1.dist-info/metadata.json
lazyEEG-0.8.0.1.dist-info/top_level.txt
