Metadata-Version: 2.0
Name: lazyEEG
Version: 0.8.0.1
Summary: An analyzer of EEG data
Home-page: UNKNOWN
Author: Jinbiao Yang
Author-email: ray306@gmail.com
License: GPL License
Requires-Dist: matplotlib
Requires-Dist: mne
Requires-Dist: numpy
Requires-Dist: pandas
Requires-Dist: permute
Requires-Dist: scipy
Requires-Dist: seaborn
Requires-Dist: statsmodels
Requires-Dist: tqdm
